LICENSE
MANIFEST.in
README.md
requirements.txt
setup.cfg
setup.py
dbmodel/__init__.py
dbmodel.egg-info/PKG-INFO
dbmodel.egg-info/SOURCES.txt
dbmodel.egg-info/dependency_links.txt
dbmodel.egg-info/requires.txt
dbmodel.egg-info/top_level.txt
dbmodel/context/__init__.py
dbmodel/context/connection.py
dbmodel/context/database.py
dbmodel/entity/__init__.py
dbmodel/entity/datatype.py
dbmodel/entity/entity.py
dbmodel/entity/status.py
dbmodel/utils/__init__.py
dbmodel/utils/angular.py
dbmodel/utils/inflector.py
dbmodel/utils/make.py
dbmodel/utils/singleton.py
test/test.py