Metadata-Version: 2.1
Name: dbmodel
Version: 0.1.7
Summary: Python DataBase Entity Model
Home-page: https://github.com/robertons/dbmodelpy
Author: Roberto Neves
Author-email: robertonsilva@gmail.com
License: MIT
Keywords: datamodel,database,model,entity,framework,mysql,mariadb
Platform: UNKNOWN
Classifier: Development Status :: 3 - Alpha
Classifier: Environment :: Web Environment
Classifier: Intended Audience :: Developers
Classifier: Natural Language :: English
Classifier: Natural Language :: Portuguese (Brazilian)
Classifier: License :: OSI Approved :: MIT License
Classifier: Programming Language :: Python :: 3.6
